setup.py
mirage/hello.py
mirage_rce.egg-info/PKG-INFO
mirage_rce.egg-info/SOURCES.txt
mirage_rce.egg-info/dependency_links.txt
mirage_rce.egg-info/top_level.txt