Metadata-Version: 2.1
Name: mirage_rce
Version: 0.0.1
Summary: install this module then reverse shell
Author: mirage
